dsa_alg/__init__.py
dsa_alg/search.py
dsa_alg/sorting.py
dsa_alg-0.1.3.dist-info/LICENSE
dsa_alg-0.1.3.dist-info/METADATA
dsa_alg-0.1.3.dist-info/WHEEL
dsa_alg-0.1.3.dist-info/top_level.txt
dsa_alg-0.1.3.dist-info/RECORD
