Metadata-Version: 2.1
Name: dsa-alg
Version: 0.1.3
Summary: Datastructures and Algorithm Library
Home-page: https://dsa-alg.readthedocs.io/
Author: Praveen Kumar Rajendran
Author-email: praveenrajendran@gmail.com
License: MIT
Classifier: Intended Audience :: Developers
Classifier: License :: OSI Approved :: MIT License
Classifier: Programming Language :: Python
Classifier: Programming Language :: Python :: 3
Classifier: Programming Language :: Python :: 3.6
Classifier: Programming Language :: Python :: 3.7
Classifier: Programming Language :: Python :: 3.8
Classifier: Programming Language :: Python :: 3.9
Classifier: Operating System :: OS Independent
License-File: LICENSE
